scout_apm_logging/__init__.py
scout_apm_logging/handler.py
scout_apm_logging/utils/__init__.py
scout_apm_logging/utils/operation_utils.py
scout_apm_logging-1.0.3.dist-info/METADATA
scout_apm_logging-1.0.3.dist-info/WHEEL
scout_apm_logging-1.0.3.dist-info/RECORD
