Metadata-Version: 2.4
Name: scout-apm-logging
Version: 1.0.3
Summary: Scout APM Python Logging Agent
Author: Scout
Author-email: support@scoutapm.com
Maintainer: Quinn Milionis
Maintainer-email: quinn@scoutapm.com
Requires-Python: >=3.10,<4.0
Classifier: Programming Language :: Python :: 3
Classifier: Programming Language :: Python :: 3.10
Classifier: Programming Language :: Python :: 3.11
Classifier: Programming Language :: Python :: 3.12
Classifier: Programming Language :: Python :: 3.13
Classifier: Programming Language :: Python :: 3.14
Requires-Dist: opentelemetry-api (>=1.26.0,<2.0.0)
Requires-Dist: opentelemetry-exporter-otlp (>=1.26.0,<2.0.0)
Requires-Dist: opentelemetry-sdk (>=1.26.0,<2.0.0)
Requires-Dist: scout-apm (>=3.1.0,<4.0.0)
Project-URL: documentation, https://scoutapm.com/docs/features/log-management
Project-URL: homepage, https://scoutapm.com
Project-URL: repository, https://github.com/scoutapp/scout_apm_python_logging
